[
    {
        "id": "1",
        "quotation": "everything is like cotton until it gets wet and heavy...",
        "published": "2018-07-25",
        "tag": "realization",
        "slug": "realization",
        "created_at": "1678477509771",
        "updated_at": "1678477511159",
        "published_at": "1678477511157",
        "created_by_id": "1",
        "updated_by_id": "1"
    },
    {
        "id": "2",
        "quotation": "confidence comes when you start writing yourself!",
        "published": "2018-10-10",
        "tag": "confidence",
        "slug": "confidence",
        "created_at": "1678516336903",
        "updated_at": "1678516338556",
        "published_at": "1678516338554",
        "created_by_id": "1",
        "updated_by_id": "1"
    },
    {
        "id": "3",
        "quotation": "everything about love is fragile...\nfrom building trust to making confessions...",
        "published": "2018-10-18",
        "tag": "love",
        "slug": "love",
        "created_at": "1678516430951",
        "updated_at": "1678516431867",
        "published_at": "1678516431864",
        "created_by_id": "1",
        "updated_by_id": "1"
    },
    {
        "id": "4",
        "quotation": "from goodnights to goodbyes...",
        "published": "2018-10-31",
        "tag": "heartbreak",
        "slug": "heartbreak",
        "created_at": "1678516490982",
        "updated_at": "1678516491970",
        "published_at": "1678516491968",
        "created_by_id": "1",
        "updated_by_id": "1"
    },
    {
        "id": "5",
        "quotation": "every achievable thing is not a success...",
        "published": "2018-11-19",
        "tag": "dreams",
        "slug": "dreams",
        "created_at": "1678516574414",
        "updated_at": "1678516575462",
        "published_at": "1678516575461",
        "created_by_id": "1",
        "updated_by_id": "1"
    },
    {
        "id": "6",
        "quotation": "consuming your own skin just because you want success isn't called hard work;\nlife matters idiot...",
        "published": "2018-11-01",
        "tag": "suicide",
        "slug": "suicide",
        "created_at": "1678516672376",
        "updated_at": "1678516673435",
        "published_at": "1678516673431",
        "created_by_id": "1",
        "updated_by_id": "1"
    },
    {
        "id": "7",
        "quotation": "don't let your soul forget speech,\nbe his voice.",
        "published": "2018-11-07",
        "tag": "soul",
        "slug": "soul",
        "created_at": "1678516989460",
        "updated_at": "1678516990432",
        "published_at": "1678516990430",
        "created_by_id": "1",
        "updated_by_id": "1"
    },
    {
        "id": "8",
        "quotation": "they can bully you,\nbut can they be you?",
        "published": "2018-11-21",
        "tag": "bullying",
        "slug": "bullying",
        "created_at": "1678517228287",
        "updated_at": "1678517229459",
        "published_at": "1678517229457",
        "created_by_id": "1",
        "updated_by_id": "1"
    },
    {
        "id": "9",
        "quotation": "he tried to grab money with both hands\nbut forgot that he accidentally lost hold on mine",
        "published": "2019-08-15",
        "tag": "greed",
        "slug": "greed",
        "created_at": "1678947163356",
        "updated_at": "1678947166632",
        "published_at": "1678947166630",
        "created_by_id": "1",
        "updated_by_id": "1"
    },
    {
        "id": "10",
        "quotation": "emptiness that consumed a lonely soul\nyet all she ever did was smile",
        "published": "2019-08-07",
        "tag": "fake smile",
        "slug": "fake-smile",
        "created_at": "1678961995804",
        "updated_at": "1678961996741",
        "published_at": "1678961996740",
        "created_by_id": "1",
        "updated_by_id": "1"
    },
    {
        "id": "11",
        "quotation": "every culture seems valid\nuntil you're cancelled within it!",
        "published": "2019-08-14",
        "tag": "fake beauty",
        "slug": "fake-beauty",
        "created_at": "1678962342986",
        "updated_at": "1678962343836",
        "published_at": "1678962343834",
        "created_by_id": "1",
        "updated_by_id": "1"
    }
]